{
    "isSuccess": true,
    "status": "Дані успішно знайдено",
    "data": {
        "userId": "a98d501f-98f2-4497-b263-964bf5e04cda",
        "success": {
            "16349519": "fa83b9ce-d990-4613-9c94-d5d65c5555dc"
        },
        "withError": [],
        "reportRef": "https://vkursi.pro/movableloads/getallmovablepage?number=16349519&id=fa83b9ce-d990-4613-9c94-d5d65c5555dc",
        "report": {
            "createdOn": "2020-03-19T11:45:53",
            "dataObject": "{\"ID\":17374040,\"opOpID\":16349519,\"lmType\":\"застава рухомого майна\",\"opStatus\":\"1\",\"opType\":\"3\",\"actTerm\":\"2022-07-03T00:00:00Z\",\"archiveDate\":null,\"execTerm\":\"2020-03-10T00:00:00Z\",\"prevRegistration\":null,\"reqReqID\":70609415,\"bnBnID\":null,\"regNum\":\"17374040\",\"contractSum\":\"250500000,00\",\"checkSum\":\"Д600ВАВДВА\",\"archiveNum\":null,\"penaltyInit\":null,\"currencyType\":\"гривня\",\"lmSort\":\"приватне обтяження\",\"alPossible\":\"заборонено відчужувати\",\"lmTypeExtension\":null,\"additional\":\"За Кредитним договором №20-1469/2-1 від 25.04.2012 р.: сплатити проценти, неустойку (пеню, штрафи), збитки у розмірі та у випадках, передбачених Кредитним договором\",\"archRegName\":null,\"regDate\":\"2017-07-03T19:01:29Z\",\"currentObjID\":75145,\"startDay\":null,\"startMonth\":null,\"startYear\":null,\"validContractSum\":250500000,\"properties\":[{\"ID\":16126712,\"prParentID\":null,\"prPrID\":null,\"opOpID\":17374040,\"adAdID\":null,\"reReID\":null,\"reLandRegNumHash\":null,\"reLetterHash\":null,\"reCadNumHash\":null,\"mvRegNum\":\"17392АН\",\"prType\":\"інший транспортний засіб\",\"reLandRegNum\":null,\"reLandType\":null,\"reLetter\":null,\"reCadNum\":null,\"changeType\":\"5\",\"prCategory\":\"3\",\"mvSrNum\":\"371676023\",\"otherRegNum\":null,\"mvSrNumHash\":\"371676023\",\"mvRegNumHash\":\"17392ah\",\"otherRegNumHash\":null,\"additional\":null,\"prTypeExtension\":\"Комбайн зернозбиральний NEW HOLLAND CSX7080 2008 р.в. \",\"reLandTypeExtension\":null,\"otherRegNumNID\":null,\"isArchive\":null,\"prRegNum\":null,\"prRegNumNID\":null,\"driRegDate\":null,\"driRegNum\":null,\"fullExtension\":\"Комбайн зернозбиральний NEW HOLLAND CSX7080 2008 р.в. \",\"prAttr\":[],\"prTypeAttr\":[{\"xtype\":\"textfield\",\"name\":\"prRegNum\",\"fieldLabel\":\"Реєстраційний номер майна\",\"attrTyp\":\"static\",\"dataType\":3,\"enforceMaxLength\":true,\"daRnNum\":2,\"width\":\"100%\",\"flex\":1,\"allowBlank\":true,\"maxLength\":1000,\"vtype\":\"charset3Validator\"},{\"xtype\":\"textfield\",\"name\":\"mvSrNum\",\"fieldLabel\":\"Серійний номер\",\"attrTyp\":\"static\",\"dataType\":3,\"enforceMaxLength\":true,\"daRnNum\":7,\"width\":\"100%\",\"flex\":1,\"allowBlank\":true,\"maxLength\":240,\"vtype\":\"charset3Validator\"},{\"xtype\":\"textfield\",\"name\":\"prTypeExtension\",\"fieldLabel\":\"Доповнення до типу\",\"attrTyp\":\"static\",\"dataType\":3,\"enforceMaxLength\":true,\"daRnNum\":1,\"width\":\"100%\",\"flex\":1,\"allowBlank\":false,\"maxLength\":2000,\"vtype\":\"charset3Validator\"},{\"xtype\":\"textfield\",\"name\":\"mvRegNum\",\"fieldLabel\":\"Номер держ. реєстрації\",\"attrTyp\":\"static\",\"dataType\":3,\"enforceMaxLength\":true,\"daRnNum\":6,\"width\":\"100%\",\"flex\":1,\"allowBlank\":true,\"maxLength\":240,\"vtype\":\"charset3Validator\"}],\"addProperties\":\"інший транспортний засіб, Комбайн зернозбиральний NEW HOLLAND CSX7080 2008 р.в. , Номер об`єкта: 371676023, Номер державної реєстрації: 17392АН\"},{\"ID\":16126713,\"prParentID\":null,\"prPrID\":null,\"opOpID\":17374040,\"adAdID\":null,\"reReID\":null,\"reLandRegNumHash\":null,\"reLetterHash\":null,\"reCadNumHash\":null,\"mvRegNum\":\"17200 АН\",\"prType\":\"інший транспортний засіб\",\"reLandRegNum\":null,\"reLandType\":null,\"reLetter\":null,\"reCadNum\":null,\"changeType\":\"5\",\"prCategory\":\"3\",\"mvSrNum\":\"371632029\",\"otherRegNum\":null,\"mvSrNumHash\":\"371632029\",\"mvRegNumHash\":\"17200ah\",\"otherRegNumHash\":null,\"additional\":null,\"prTypeExtension\":\"Комбайн NEW HOLLAND CSX7080, 2008 р.в., двигун 6312\",\"reLandTypeExtension\":null,\"otherRegNumNID\":null,\"isArchive\":null,\"prRegNum\":null,\"prRegNumNID\":null,\"driRegDate\":null,\"driRegNum\":null,\"fullExtension\":\"Комбайн NEW HOLLAND CSX7080, 2008 р.в., двигун 6312\",\"prAttr\":[],\"prTypeAttr\":[{\"xtype\":\"textfield\",\"name\":\"prRegNum\",\"fieldLabel\":\"Реєстраційний номер майна\",\"attrTyp\":\"static\",\"dataType\":3,\"enforceMaxLength\":true,\"daRnNum\":2,\"width\":\"100%\",\"flex\":1,\"allowBlank\":true,\"maxLength\":1000,\"vtype\":\"charset3Validator\"},{\"xtype\":\"textfield\",\"name\":\"mvSrNum\",\"fieldLabel\":\"Серійний номер\",\"attrTyp\":\"static\",\"dataType\":3,\"enforceMaxLength\":true,\"daRnNum\":7,\"width\":\"100%\",\"flex\":1,\"allowBlank\":true,\"maxLength\":240,\"vtype\":\"charset3Validator\"},{\"xtype\":\"textfield\",\"name\":\"prTypeExtension\",\"fieldLabel\":\"Доповнення до типу\",\"attrTyp\":\"static\",\"dataType\":3,\"enforceMaxLength\":true,\"daRnNum\":1,\"width\":\"100%\",\"flex\":1,\"allowBlank\":false,\"maxLength\":2000,\"vtype\":\"charset3Validator\"},{\"xtype\":\"textfield\",\"name\":\"mvRegNum\",\"fieldLabel\":\"Номер держ. реєстрації\",\"attrTyp\":\"static\",\"dataType\":3,\"enforceMaxLength\":true,\"daRnNum\":6,\"width\":\"100%\",\"flex\":1,\"allowBlank\":true,\"maxLength\":240,\"vtype\":\"charset3Validator\"}],\"addProperties\":\"інший транспортний засіб, Комбайн NEW HOLLAND CSX7080, 2008 р.в., двигун 6312, Номер об`єкта: 371632029, Номер державної реєстрації: 17200 АН\"},{\"ID\":16126714,\"prParentID\":15556454,\"prPrID\":null,\"opOpID\":17374040,\"adAdID\":null,\"reReID\":null,\"reLandRegNumHash\":null,\"reLetterHash\":null,\"reCadNumHash\":null,\"mvRegNum\":\"17364 АН\",\"prType\":\"інший транспортний засіб\",\"reLandRegNum\":null,\"reLandType\":null,\"reLetter\":null,\"reCadNum\":null,\"changeType\":\"5\",\"prCategory\":\"3\",\"mvSrNum\":\"Z8RW01204\",\"otherRegNum\":null,\"mvSrNumHash\":\"z8rw01204\",\"mvRegNumHash\":\"17364ah\",\"otherRegNumHash\":null,\"additional\":null,\"prTypeExtension\":\"Трактор NEW HOLLAND T8040, 2008 р.в., двигун 46841277\",\"reLandTypeExtension\":null,\"otherRegNumNID\":null,\"isArchive\":null,\"prRegNum\":null,\"prRegNumNID\":null,\"driRegDate\":null,\"driRegNum\":null,\"fullExtension\":\"Трактор NEW HOLLAND T8040, 2008 р.в., двигун 46841277\",\"prAttr\":[],\"prTypeAttr\":[{\"xtype\":\"textfield\",\"name\":\"prRegNum\",\"fieldLabel\":\"Реєстраційний номер майна\",\"attrTyp\":\"static\",\"dataType\":3,\"enforceMaxLength\":true,\"daRnNum\":2,\"width\":\"100%\",\"flex\":1,\"allowBlank\":true,\"maxLength\":1000,\"vtype\":\"charset3Validator\"},{\"xtype\":\"textfield\",\"name\":\"mvSrNum\",\"fieldLabel\":\"Серійний номер\",\"attrTyp\":\"static\",\"dataType\":3,\"enforceMaxLength\":true,\"daRnNum\":7,\"width\":\"100%\",\"flex\":1,\"allowBlank\":true,\"maxLength\":240,\"vtype\":\"charset3Validator\"},{\"xtype\":\"textfield\",\"name\":\"prTypeExtension\",\"fieldLabel\":\"Доповнення до типу\",\"attrTyp\":\"static\",\"dataType\":3,\"enforceMaxLength\":true,\"daRnNum\":1,\"width\":\"100%\",\"flex\":1,\"allowBlank\":false,\"maxLength\":2000,\"vtype\":\"charset3Validator\"},{\"xtype\":\"textfield\",\"name\":\"mvRegNum\",\"fieldLabel\":\"Номер держ. реєстрації\",\"attrTyp\":\"static\",\"dataType\":3,\"enforceMaxLength\":true,\"daRnNum\":6,\"width\":\"100%\",\"flex\":1,\"allowBlank\":true,\"maxLength\":240,\"vtype\":\"charset3Validator\"}],\"addProperties\":\"інший транспортний засіб, Трактор NEW HOLLAND T8040, 2008 р.в., двигун 46841277, Номер об`єкта: Z8RW01204, Номер державної реєстрації: 17364 АН\"}],\"subjects\":[{\"ID\":21778740,\"sbjType\":\"2\",\"subjectParentID\":null,\"rusNID\":null,\"atuAtuID\":null,\"cnCnID\":null,\"rlRlID\":10,\"opOpID\":17374040,\"ukrNID\":5323486,\"foreignSubject\":null,\"birthMonth\":null,\"codeAbsence\":\"\",\"code\":\"34550446\",\"changeType\":\"3\",\"birthYear\":null,\"birthDay\":null,\"addressIndex\":null,\"additional\":null,\"birthPlace\":null,\"name\":\"Дочірнє підприємство Ілліч-Агро Донбас Публічного акціонерного товариства \\\"Маріупольський металургійний комбінат імені Ілліча \\\"\",\"simpleAddress\":\"87504, Донецька обл., м. Маріуполь, вул. Семашка, буд.15, кімн.405\",\"addressDetails\":null,\"document\":null,\"rusName\":null,\"fullName\":\"Дочірнє підприємство Ілліч-Агро Донбас Публічного акціонерного товариства \\\"Маріупольський металургійний комбінат імені Ілліча \\\"\",\"dcCountry\":null,\"room\":null,\"dcRoomType\":\"\",\"dcBuildingType\":\"\",\"building\":null,\"dcObjectNumType\":\"\",\"objectNum\":null,\"dcHouseType\":\"\",\"house\":null,\"streetAtuID\":null,\"phone\":null,\"rlName\":\"Боржник\",\"addSubject\":\"Дочірнє підприємство Ілліч-Агро Донбас Публічного акціонерного товариства \\\"Маріупольський металургійний комбінат імені Ілліча \\\", код: 34550446\"},{\"ID\":21778739,\"sbjType\":\"2\",\"subjectParentID\":null,\"rusNID\":null,\"atuAtuID\":null,\"cnCnID\":null,\"rlRlID\":11,\"opOpID\":17374040,\"ukrNID\":3232240,\"foreignSubject\":null,\"birthMonth\":null,\"codeAbsence\":\"\",\"code\":\"00039002\",\"changeType\":\"3\",\"birthYear\":null,\"birthDay\":null,\"addressIndex\":null,\"additional\":null,\"birthPlace\":null,\"name\":\"Публічне акціонерне товариство \\\"Акціонерний комерційний промислово-інвестиційний банк\\\"\",\"simpleAddress\":\"Україна, 01001, м. Київ, провулок Шевченка, 12\",\"addressDetails\":null,\"document\":null,\"rusName\":null,\"fullName\":\"Публічне акціонерне товариство \\\"Акціонерний комерційний промислово-інвестиційний банк\\\"\",\"dcCountry\":null,\"room\":null,\"dcRoomType\":\"\",\"dcBuildingType\":\"\",\"building\":null,\"dcObjectNumType\":\"\",\"objectNum\":null,\"dcHouseType\":\"\",\"house\":null,\"streetAtuID\":null,\"phone\":null,\"rlName\":\"Обтяжувач\",\"addSubject\":\"Публічне акціонерне товариство \\\"Акціонерний комерційний промислово-інвестиційний банк\\\", код: 00039002\"}],\"causeDocuments\":[{\"ID\":14330470,\"opOpID\":16349519,\"pubDate\":\"2017-06-30T00:00:00Z\",\"cdType\":\"999\",\"serNum\":\"1414\",\"additional\":null,\"publisher\":\"ПН КМНО Бадахов Ю.Н\",\"cdTypeExtension\":\"ДОГОВІР ЗАСТАВИ ТРАНСПОРТНИХ ЗАСОБІВ № 20-1469/2-1-30062017/з9 \",\"cdParentID\":null,\"changeType\":\"1\",\"causeDocumentInfo\":\"ДОГОВІР ЗАСТАВИ ТРАНСПОРТНИХ ЗАСОБІВ № 20-1469/2-1-30062017/з9 , серія та номер: 1414, виданий: 30.06.2017, видавник: ПН КМНО Бадахов Ю.Н\"},{\"ID\":14760640,\"opOpID\":16877231,\"pubDate\":\"2018-05-15T00:00:00Z\",\"cdType\":\"999\",\"serNum\":\"р.№1008\",\"additional\":null,\"publisher\":\"Приватний нотаріус Київського міського нотаріального округу Бадахов Ю.Н.\",\"cdTypeExtension\":\"Договір про внесення змін №20-1469/2-1-15052018/з7 до Договору застави транспортних засобів №20-1469/2-1-30062017/з9, посвідченого ПН КМНО Бадаховим Ю.Н. 30.06.2017 р. за р.№1414\",\"cdParentID\":null,\"changeType\":\"1\",\"causeDocumentInfo\":\"Договір про внесення змін №20-1469/2-1-15052018/з7 до Договору застави транспортних засобів №20-1469/2-1-30062017/з9, посвідченого ПН КМНО Бадаховим Ю.Н. 30.06.2017 р. за р.№1414, серія та номер: р.№1008, виданий: 15.05.2018, видавник: Приватний нотаріус Київського міського нотаріального округу Бадахов Ю.Н.\"},{\"ID\":14796446,\"opOpID\":16919857,\"pubDate\":\"2018-05-31T00:00:00Z\",\"cdType\":\"999\",\"serNum\":\"20-1469/2-1-31052018/з1,р.1231\",\"additional\":null,\"publisher\":\"Приватний нотаріус Київського міського нотаріального округу Бадахов Ю.Н.\",\"cdTypeExtension\":\"Договір про внесення змін до договору застави транспортних засобів № 20-1469/2-1-30062017/з9 від 30.06.2017 р., р. № 1414 \",\"cdParentID\":null,\"changeType\":\"1\",\"causeDocumentInfo\":\"Договір про внесення змін до договору застави транспортних засобів № 20-1469/2-1-30062017/з9 від 30.06.2017 р., р. № 1414 , серія та номер: 20-1469/2-1-31052018/з1,р.1231, виданий: 31.05.2018, видавник: Приватний нотаріус Київського міського нотаріального округу Бадахов Ю.Н.\"},{\"ID\":15186313,\"opOpID\":17374040,\"pubDate\":\"2019-03-28T00:00:00Z\",\"cdType\":\"999\",\"serNum\":\"20-1469/2-1-28032019/з7,р1291\",\"additional\":null,\"publisher\":\"Приватний нотаріус Київського міського нотаріального округу Бадахов Ю.Н.\",\"cdTypeExtension\":\"договір про внесення змін до договору застави транспортних засобів № 20-1469/2-1-30062017/з9 від 30.06.2017 р. (р.1414)\",\"cdParentID\":null,\"changeType\":\"1\",\"causeDocumentInfo\":\"договір про внесення змін до договору застави транспортних засобів № 20-1469/2-1-30062017/з9 від 30.06.2017 р. (р.1414), серія та номер: 20-1469/2-1-28032019/з7,р1291, виданий: 28.03.2019, видавник: Приватний нотаріус Київського міського нотаріального округу Бадахов Ю.Н.\"}],\"opRegDate\":\"2019-03-29T14:03:27Z\",\"registrarInfo\":\"Приватний нотаріус Бадахов Ю.Н., Київський міський нотаріальний округ, м.Київ\",\"lmState\":\"1\",\"documents\":[{\"docID\":48020340,\"regNum\":55720877,\"objObjID\":75145,\"empEmpID\":110542,\"docType\":\"1\",\"generateddocument\":null,\"regDate\":\"2018-05-17T10:33:12Z\",\"seSeID\":null,\"docState\":\"1\",\"docTypeName\":\"витяг про реєстрацію\",\"empFullName\":\"Новейко-Вадіс Оксана Георгіївна, Філія Міста Києва Та Київської Області Державного Підприємства \\\"Національні Інформаційні Системи\\\"\"},{\"docID\":47536872,\"regNum\":55952883,\"objObjID\":75145,\"empEmpID\":110542,\"docType\":\"1\",\"generateddocument\":null,\"regDate\":\"2018-06-07T17:48:04Z\",\"seSeID\":null,\"docState\":\"1\",\"docTypeName\":\"витяг про реєстрацію\",\"empFullName\":\"Новейко-Вадіс Оксана Георгіївна, Філія Міста Києва Та Київської Області Державного Підприємства \\\"Національні Інформаційні Системи\\\"\"},{\"docID\":44665286,\"regNum\":52731841,\"objObjID\":74661,\"empEmpID\":105648,\"docType\":\"1\",\"generateddocument\":null,\"regDate\":\"2017-07-04T09:14:37Z\",\"seSeID\":null,\"docState\":\"1\",\"docTypeName\":\"витяг про реєстрацію\",\"empFullName\":\"Бадахов Юрій Назірович, Приватний Нотаріус Бадахов Ю.Н.\"},{\"docID\":42294040,\"regNum\":58867058,\"objObjID\":75145,\"empEmpID\":110192,\"docType\":\"1\",\"generateddocument\":\"{\\\"store\\\":\\\"drormReports\\\",\\\"fName\\\":\\\"ormUb_document generatedDocument 42294040.pdf\\\",\\\"origName\\\":\\\"42294040.pdf\\\",\\\"relPath\\\":\\\"231\\\\\\\\306\\\\\\\\\\\",\\\"ct\\\":\\\"application/pdf\\\",\\\"size\\\":299719,\\\"md5\\\":\\\"5aceb13994c677023b55f13618aad865\\\"}\",\"regDate\":\"2019-03-29T14:03:28Z\",\"seSeID\":null,\"docState\":\"1\",\"docTypeName\":\"витяг про реєстрацію\",\"empFullName\":\"Цілепа Євген Миколайович, Філія Міста Києва Та Київської Області Державного Підприємства \\\"Національні Інформаційні Системи\\\"\"}],\"lmStateName\":\"Зареєстроване\",\"currentObjName\":\"Філія міста Києва та Київської області державного підприємства \\\"Національні інформаційні системи\\\"\",\"currentRegistrar\":\"Приватний нотаріус Бадахов Ю.Н., Київський міський нотаріальний округ, м.Київ\"}",
            "dataObjectClear": {
                "id": 17374040,
                "opOpID": 16349519,
                "lmType": "застава рухомого майна",
                "opStatus": "1",
                "opType": "3",
                "actTerm": "2022-07-03T00:00:00Z",
                "archiveDate": null,
                "execTerm": "2020-03-10T00:00:00Z",
                "prevRegistration": null,
                "reqReqID": 70609415,
                "bnBnID": null,
                "regNum": "17374040",
                "contractSum": "250500000,00",
                "checkSum": "Д600ВАВДВА",
                "archiveNum": null,
                "penaltyInit": null,
                "currencyType": "гривня",
                "lmSort": "приватне обтяження",
                "alPossible": "заборонено відчужувати",
                "lmTypeExtension": null,
                "additional": "За Кредитним договором №20-1469/2-1 від 25.04.2012 р.: сплатити проценти, неустойку (пеню, штрафи), збитки у розмірі та у випадках, передбачених Кредитним договором",
                "archRegName": null,
                "regDate": "2017-07-03T19:01:29Z",
                "currentObjID": 75145,
                "startDay": null,
                "startMonth": null,
                "startYear": null,
                "validContractSum": 250500000.0,
                "properties": [
                    {
                        "id": 16126712,
                        "prParentID": null,
                        "prPrID": null,
                        "opOpID": 17374040,
                        "adAdID": null,
                        "reReID": null,
                        "reLandRegNumHash": null,
                        "reLetterHash": null,
                        "reCadNumHash": null,
                        "mvRegNum": "17392АН",
                        "prType": "інший транспортний засіб",
                        "reLandRegNum": null,
                        "reLandType": null,
                        "reLetter": null,
                        "reCadNum": null,
                        "changeType": "5",
                        "prCategory": "3",
                        "mvSrNum": "371676023",
                        "otherRegNum": null,
                        "mvSrNumHash": "371676023",
                        "mvRegNumHash": "17392ah",
                        "otherRegNumHash": null,
                        "additional": null,
                        "prTypeExtension": "Комбайн зернозбиральний NEW HOLLAND CSX7080 2008 р.в. ",
                        "reLandTypeExtension": null,
                        "otherRegNumNID": null,
                        "isArchive": null,
                        "prRegNum": null,
                        "prRegNumNID": null,
                        "driRegDate": null,
                        "driRegNum": null,
                        "fullExtension": "Комбайн зернозбиральний NEW HOLLAND CSX7080 2008 р.в. ",
                        "prAttr": [],
                        "prTypeAttr": [
                            {
                                "xtype": "textfield",
                                "name": "prRegNum",
                                "fieldLabel": "Реєстраційний номер майна",
                                "attrTyp": "static",
                                "dataType": 3,
                                "enforceMaxLength": true,
                                "daRnNum": 2,
                                "width": "100%",
                                "flex": 1,
                                "allowBlank": true,
                                "maxLength": 1000,
                                "vtype": "charset3Validator"
                            },
                            {
                                "xtype": "textfield",
                                "name": "mvSrNum",
                                "fieldLabel": "Серійний номер",
                                "attrTyp": "static",
                                "dataType": 3,
                                "enforceMaxLength": true,
                                "daRnNum": 7,
                                "width": "100%",
                                "flex": 1,
                                "allowBlank": true,
                                "maxLength": 240,
                                "vtype": "charset3Validator"
                            },
                            {
                                "xtype": "textfield",
                                "name": "prTypeExtension",
                                "fieldLabel": "Доповнення до типу",
                                "attrTyp": "static",
                                "dataType": 3,
                                "enforceMaxLength": true,
                                "daRnNum": 1,
                                "width": "100%",
                                "flex": 1,
                                "allowBlank": false,
                                "maxLength": 2000,
                                "vtype": "charset3Validator"
                            },
                            {
                                "xtype": "textfield",
                                "name": "mvRegNum",
                                "fieldLabel": "Номер держ. реєстрації",
                                "attrTyp": "static",
                                "dataType": 3,
                                "enforceMaxLength": true,
                                "daRnNum": 6,
                                "width": "100%",
                                "flex": 1,
                                "allowBlank": true,
                                "maxLength": 240,
                                "vtype": "charset3Validator"
                            }
                        ],
                        "addProperties": "інший транспортний засіб, Комбайн зернозбиральний NEW HOLLAND CSX7080 2008 р.в. , Номер об`єкта: 371676023, Номер державної реєстрації: 17392АН"
                    },
                    {
                        "id": 16126713,
                        "prParentID": null,
                        "prPrID": null,
                        "opOpID": 17374040,
                        "adAdID": null,
                        "reReID": null,
                        "reLandRegNumHash": null,
                        "reLetterHash": null,
                        "reCadNumHash": null,
                        "mvRegNum": "17200 АН",
                        "prType": "інший транспортний засіб",
                        "reLandRegNum": null,
                        "reLandType": null,
                        "reLetter": null,
                        "reCadNum": null,
                        "changeType": "5",
                        "prCategory": "3",
                        "mvSrNum": "371632029",
                        "otherRegNum": null,
                        "mvSrNumHash": "371632029",
                        "mvRegNumHash": "17200ah",
                        "otherRegNumHash": null,
                        "additional": null,
                        "prTypeExtension": "Комбайн NEW HOLLAND CSX7080, 2008 р.в., двигун 6312",
                        "reLandTypeExtension": null,
                        "otherRegNumNID": null,
                        "isArchive": null,
                        "prRegNum": null,
                        "prRegNumNID": null,
                        "driRegDate": null,
                        "driRegNum": null,
                        "fullExtension": "Комбайн NEW HOLLAND CSX7080, 2008 р.в., двигун 6312",
                        "prAttr": [],
                        "prTypeAttr": [
                            {
                                "xtype": "textfield",
                                "name": "prRegNum",
                                "fieldLabel": "Реєстраційний номер майна",
                                "attrTyp": "static",
                                "dataType": 3,
                                "enforceMaxLength": true,
                                "daRnNum": 2,
                                "width": "100%",
                                "flex": 1,
                                "allowBlank": true,
                                "maxLength": 1000,
                                "vtype": "charset3Validator"
                            },
                            {
                                "xtype": "textfield",
                                "name": "mvSrNum",
                                "fieldLabel": "Серійний номер",
                                "attrTyp": "static",
                                "dataType": 3,
                                "enforceMaxLength": true,
                                "daRnNum": 7,
                                "width": "100%",
                                "flex": 1,
                                "allowBlank": true,
                                "maxLength": 240,
                                "vtype": "charset3Validator"
                            },
                            {
                                "xtype": "textfield",
                                "name": "prTypeExtension",
                                "fieldLabel": "Доповнення до типу",
                                "attrTyp": "static",
                                "dataType": 3,
                                "enforceMaxLength": true,
                                "daRnNum": 1,
                                "width": "100%",
                                "flex": 1,
                                "allowBlank": false,
                                "maxLength": 2000,
                                "vtype": "charset3Validator"
                            },
                            {
                                "xtype": "textfield",
                                "name": "mvRegNum",
                                "fieldLabel": "Номер держ. реєстрації",
                                "attrTyp": "static",
                                "dataType": 3,
                                "enforceMaxLength": true,
                                "daRnNum": 6,
                                "width": "100%",
                                "flex": 1,
                                "allowBlank": true,
                                "maxLength": 240,
                                "vtype": "charset3Validator"
                            }
                        ],
                        "addProperties": "інший транспортний засіб, Комбайн NEW HOLLAND CSX7080, 2008 р.в., двигун 6312, Номер об`єкта: 371632029, Номер державної реєстрації: 17200 АН"
                    },
                    {
                        "id": 16126714,
                        "prParentID": 15556454,
                        "prPrID": null,
                        "opOpID": 17374040,
                        "adAdID": null,
                        "reReID": null,
                        "reLandRegNumHash": null,
                        "reLetterHash": null,
                        "reCadNumHash": null,
                        "mvRegNum": "17364 АН",
                        "prType": "інший транспортний засіб",
                        "reLandRegNum": null,
                        "reLandType": null,
                        "reLetter": null,
                        "reCadNum": null,
                        "changeType": "5",
                        "prCategory": "3",
                        "mvSrNum": "Z8RW01204",
                        "otherRegNum": null,
                        "mvSrNumHash": "z8rw01204",
                        "mvRegNumHash": "17364ah",
                        "otherRegNumHash": null,
                        "additional": null,
                        "prTypeExtension": "Трактор NEW HOLLAND T8040, 2008 р.в., двигун 46841277",
                        "reLandTypeExtension": null,
                        "otherRegNumNID": null,
                        "isArchive": null,
                        "prRegNum": null,
                        "prRegNumNID": null,
                        "driRegDate": null,
                        "driRegNum": null,
                        "fullExtension": "Трактор NEW HOLLAND T8040, 2008 р.в., двигун 46841277",
                        "prAttr": [],
                        "prTypeAttr": [
                            {
                                "xtype": "textfield",
                                "name": "prRegNum",
                                "fieldLabel": "Реєстраційний номер майна",
                                "attrTyp": "static",
                                "dataType": 3,
                                "enforceMaxLength": true,
                                "daRnNum": 2,
                                "width": "100%",
                                "flex": 1,
                                "allowBlank": true,
                                "maxLength": 1000,
                                "vtype": "charset3Validator"
                            },
                            {
                                "xtype": "textfield",
                                "name": "mvSrNum",
                                "fieldLabel": "Серійний номер",
                                "attrTyp": "static",
                                "dataType": 3,
                                "enforceMaxLength": true,
                                "daRnNum": 7,
                                "width": "100%",
                                "flex": 1,
                                "allowBlank": true,
                                "maxLength": 240,
                                "vtype": "charset3Validator"
                            },
                            {
                                "xtype": "textfield",
                                "name": "prTypeExtension",
                                "fieldLabel": "Доповнення до типу",
                                "attrTyp": "static",
                                "dataType": 3,
                                "enforceMaxLength": true,
                                "daRnNum": 1,
                                "width": "100%",
                                "flex": 1,
                                "allowBlank": false,
                                "maxLength": 2000,
                                "vtype": "charset3Validator"
                            },
                            {
                                "xtype": "textfield",
                                "name": "mvRegNum",
                                "fieldLabel": "Номер держ. реєстрації",
                                "attrTyp": "static",
                                "dataType": 3,
                                "enforceMaxLength": true,
                                "daRnNum": 6,
                                "width": "100%",
                                "flex": 1,
                                "allowBlank": true,
                                "maxLength": 240,
                                "vtype": "charset3Validator"
                            }
                        ],
                        "addProperties": "інший транспортний засіб, Трактор NEW HOLLAND T8040, 2008 р.в., двигун 46841277, Номер об`єкта: Z8RW01204, Номер державної реєстрації: 17364 АН"
                    }
                ],
                "subjects": [
                    {
                        "id": 21778740,
                        "sbjType": "2",
                        "subjectParentID": null,
                        "rusNID": null,
                        "atuAtuID": null,
                        "cnCnID": null,
                        "rlRlID": 10,
                        "opOpID": 17374040,
                        "ukrNID": 5323486,
                        "foreignSubject": null,
                        "birthMonth": null,
                        "codeAbsence": "",
                        "code": "34550446",
                        "changeType": "3",
                        "birthYear": null,
                        "birthDay": null,
                        "addressIndex": null,
                        "additional": null,
                        "birthPlace": null,
                        "name": "Дочірнє підприємство Ілліч-Агро Донбас Публічного акціонерного товариства \"Маріупольський металургійний комбінат імені Ілліча \"",
                        "simpleAddress": "87504, Донецька обл., м. Маріуполь, вул. Семашка, буд.15, кімн.405",
                        "addressDetails": null,
                        "document": null,
                        "rusName": null,
                        "fullName": "Дочірнє підприємство Ілліч-Агро Донбас Публічного акціонерного товариства \"Маріупольський металургійний комбінат імені Ілліча \"",
                        "dcCountry": null,
                        "room": null,
                        "dcRoomType": "",
                        "dcBuildingType": "",
                        "building": null,
                        "dcObjectNumType": "",
                        "objectNum": null,
                        "dcHouseType": "",
                        "house": null,
                        "streetAtuID": null,
                        "phone": null,
                        "atuAtuStr": null,
                        "rlName": "Боржник",
                        "addSubject": "Дочірнє підприємство Ілліч-Агро Донбас Публічного акціонерного товариства \"Маріупольський металургійний комбінат імені Ілліча \", код: 34550446"
                    },
                    {
                        "id": 21778739,
                        "sbjType": "2",
                        "subjectParentID": null,
                        "rusNID": null,
                        "atuAtuID": null,
                        "cnCnID": null,
                        "rlRlID": 11,
                        "opOpID": 17374040,
                        "ukrNID": 3232240,
                        "foreignSubject": null,
                        "birthMonth": null,
                        "codeAbsence": "",
                        "code": "00039002",
                        "changeType": "3",
                        "birthYear": null,
                        "birthDay": null,
                        "addressIndex": null,
                        "additional": null,
                        "birthPlace": null,
                        "name": "Публічне акціонерне товариство \"Акціонерний комерційний промислово-інвестиційний банк\"",
                        "simpleAddress": "Україна, 01001, м. Київ, провулок Шевченка, 12",
                        "addressDetails": null,
                        "document": null,
                        "rusName": null,
                        "fullName": "Публічне акціонерне товариство \"Акціонерний комерційний промислово-інвестиційний банк\"",
                        "dcCountry": null,
                        "room": null,
                        "dcRoomType": "",
                        "dcBuildingType": "",
                        "building": null,
                        "dcObjectNumType": "",
                        "objectNum": null,
                        "dcHouseType": "",
                        "house": null,
                        "streetAtuID": null,
                        "phone": null,
                        "atuAtuStr": null,
                        "rlName": "Обтяжувач",
                        "addSubject": "Публічне акціонерне товариство \"Акціонерний комерційний промислово-інвестиційний банк\", код: 00039002"
                    }
                ],
                "causeDocuments": [
                    {
                        "id": 14330470,
                        "opOpID": 16349519,
                        "pubDate": "2017-06-30T00:00:00Z",
                        "cdType": "999",
                        "serNum": "1414",
                        "additional": null,
                        "publisher": "ПН КМНО Бадахов Ю.Н",
                        "cdTypeExtension": "ДОГОВІР ЗАСТАВИ ТРАНСПОРТНИХ ЗАСОБІВ № 20-1469/2-1-30062017/з9 ",
                        "cdParentID": null,
                        "changeType": "1",
                        "causeDocumentInfo": "ДОГОВІР ЗАСТАВИ ТРАНСПОРТНИХ ЗАСОБІВ № 20-1469/2-1-30062017/з9 , серія та номер: 1414, виданий: 30.06.2017, видавник: ПН КМНО Бадахов Ю.Н"
                    },
                    {
                        "id": 14760640,
                        "opOpID": 16877231,
                        "pubDate": "2018-05-15T00:00:00Z",
                        "cdType": "999",
                        "serNum": "р.№1008",
                        "additional": null,
                        "publisher": "Приватний нотаріус Київського міського нотаріального округу Бадахов Ю.Н.",
                        "cdTypeExtension": "Договір про внесення змін №20-1469/2-1-15052018/з7 до Договору застави транспортних засобів №20-1469/2-1-30062017/з9, посвідченого ПН КМНО Бадаховим Ю.Н. 30.06.2017 р. за р.№1414",
                        "cdParentID": null,
                        "changeType": "1",
                        "causeDocumentInfo": "Договір про внесення змін №20-1469/2-1-15052018/з7 до Договору застави транспортних засобів №20-1469/2-1-30062017/з9, посвідченого ПН КМНО Бадаховим Ю.Н. 30.06.2017 р. за р.№1414, серія та номер: р.№1008, виданий: 15.05.2018, видавник: Приватний нотаріус Київського міського нотаріального округу Бадахов Ю.Н."
                    },
                    {
                        "id": 14796446,
                        "opOpID": 16919857,
                        "pubDate": "2018-05-31T00:00:00Z",
                        "cdType": "999",
                        "serNum": "20-1469/2-1-31052018/з1,р.1231",
                        "additional": null,
                        "publisher": "Приватний нотаріус Київського міського нотаріального округу Бадахов Ю.Н.",
                        "cdTypeExtension": "Договір про внесення змін до договору застави транспортних засобів № 20-1469/2-1-30062017/з9 від 30.06.2017 р., р. № 1414 ",
                        "cdParentID": null,
                        "changeType": "1",
                        "causeDocumentInfo": "Договір про внесення змін до договору застави транспортних засобів № 20-1469/2-1-30062017/з9 від 30.06.2017 р., р. № 1414 , серія та номер: 20-1469/2-1-31052018/з1,р.1231, виданий: 31.05.2018, видавник: Приватний нотаріус Київського міського нотаріального округу Бадахов Ю.Н."
                    },
                    {
                        "id": 15186313,
                        "opOpID": 17374040,
                        "pubDate": "2019-03-28T00:00:00Z",
                        "cdType": "999",
                        "serNum": "20-1469/2-1-28032019/з7,р1291",
                        "additional": null,
                        "publisher": "Приватний нотаріус Київського міського нотаріального округу Бадахов Ю.Н.",
                        "cdTypeExtension": "договір про внесення змін до договору застави транспортних засобів № 20-1469/2-1-30062017/з9 від 30.06.2017 р. (р.1414)",
                        "cdParentID": null,
                        "changeType": "1",
                        "causeDocumentInfo": "договір про внесення змін до договору застави транспортних засобів № 20-1469/2-1-30062017/з9 від 30.06.2017 р. (р.1414), серія та номер: 20-1469/2-1-28032019/з7,р1291, виданий: 28.03.2019, видавник: Приватний нотаріус Київського міського нотаріального округу Бадахов Ю.Н."
                    }
                ],
                "opRegDate": "2019-03-29T14:03:27Z",
                "registrarInfo": "Приватний нотаріус Бадахов Ю.Н., Київський міський нотаріальний округ, м.Київ",
                "lmState": "1",
                "documents": [
                    {
                        "docID": 48020340,
                        "regNum": 55720877,
                        "objObjID": 75145,
                        "empEmpID": 110542,
                        "docType": "1",
                        "generateddocument": null,
                        "regDate": "2018-05-17T10:33:12Z",
                        "seSeID": null,
                        "docState": "1",
                        "docTypeName": "витяг про реєстрацію",
                        "empFullName": "Новейко-Вадіс Оксана Георгіївна, Філія Міста Києва Та Київської Області Державного Підприємства \"Національні Інформаційні Системи\""
                    },
                    {
                        "docID": 47536872,
                        "regNum": 55952883,
                        "objObjID": 75145,
                        "empEmpID": 110542,
                        "docType": "1",
                        "generateddocument": null,
                        "regDate": "2018-06-07T17:48:04Z",
                        "seSeID": null,
                        "docState": "1",
                        "docTypeName": "витяг про реєстрацію",
                        "empFullName": "Новейко-Вадіс Оксана Георгіївна, Філія Міста Києва Та Київської Області Державного Підприємства \"Національні Інформаційні Системи\""
                    },
                    {
                        "docID": 44665286,
                        "regNum": 52731841,
                        "objObjID": 74661,
                        "empEmpID": 105648,
                        "docType": "1",
                        "generateddocument": null,
                        "regDate": "2017-07-04T09:14:37Z",
                        "seSeID": null,
                        "docState": "1",
                        "docTypeName": "витяг про реєстрацію",
                        "empFullName": "Бадахов Юрій Назірович, Приватний Нотаріус Бадахов Ю.Н."
                    },
                    {
                        "docID": 42294040,
                        "regNum": 58867058,
                        "objObjID": 75145,
                        "empEmpID": 110192,
                        "docType": "1",
                        "generateddocument": "{\"store\":\"drormReports\",\"fName\":\"ormUb_document generatedDocument 42294040.pdf\",\"origName\":\"42294040.pdf\",\"relPath\":\"231\\\\306\\\\\",\"ct\":\"application/pdf\",\"size\":299719,\"md5\":\"5aceb13994c677023b55f13618aad865\"}",
                        "regDate": "2019-03-29T14:03:28Z",
                        "seSeID": null,
                        "docState": "1",
                        "docTypeName": "витяг про реєстрацію",
                        "empFullName": "Цілепа Євген Миколайович, Філія Міста Києва Та Київської Області Державного Підприємства \"Національні Інформаційні Системи\""
                    }
                ],
                "lmStateName": "Зареєстроване",
                "currentObjName": "Філія міста Києва та Київської області державного підприємства \"Національні інформаційні системи\"",
                "currentRegistrar": "Приватний нотаріус Бадахов Ю.Н., Київський міський нотаріальний округ, м.Київ",
                "penalty": null
            }
        }
    }
}